prelude_python_sdk/__init__.py
prelude_python_sdk/_base_client.py
prelude_python_sdk/_client.py
prelude_python_sdk/_compat.py
prelude_python_sdk/_constants.py
prelude_python_sdk/_exceptions.py
prelude_python_sdk/_files.py
prelude_python_sdk/_models.py
prelude_python_sdk/_qs.py
prelude_python_sdk/_resource.py
prelude_python_sdk/_response.py
prelude_python_sdk/_streaming.py
prelude_python_sdk/_types.py
prelude_python_sdk/_version.py
prelude_python_sdk/py.typed
prelude_python_sdk/_utils/__init__.py
prelude_python_sdk/_utils/_compat.py
prelude_python_sdk/_utils/_datetime_parse.py
prelude_python_sdk/_utils/_logs.py
prelude_python_sdk/_utils/_proxy.py
prelude_python_sdk/_utils/_reflection.py
prelude_python_sdk/_utils/_resources_proxy.py
prelude_python_sdk/_utils/_streams.py
prelude_python_sdk/_utils/_sync.py
prelude_python_sdk/_utils/_transform.py
prelude_python_sdk/_utils/_typing.py
prelude_python_sdk/_utils/_utils.py
prelude_python_sdk/lib/.keep
prelude_python_sdk/resources/__init__.py
prelude_python_sdk/resources/lookup.py
prelude_python_sdk/resources/notify.py
prelude_python_sdk/resources/transactional.py
prelude_python_sdk/resources/verification.py
prelude_python_sdk/resources/verification_management.py
prelude_python_sdk/resources/watch.py
prelude_python_sdk/types/__init__.py
prelude_python_sdk/types/lookup_lookup_params.py
prelude_python_sdk/types/lookup_lookup_response.py
prelude_python_sdk/types/notify_get_subscription_config_response.py
prelude_python_sdk/types/notify_get_subscription_phone_number_response.py
prelude_python_sdk/types/notify_list_subscription_configs_params.py
prelude_python_sdk/types/notify_list_subscription_configs_response.py
prelude_python_sdk/types/notify_list_subscription_phone_number_events_params.py
prelude_python_sdk/types/notify_list_subscription_phone_number_events_response.py
prelude_python_sdk/types/notify_list_subscription_phone_numbers_params.py
prelude_python_sdk/types/notify_list_subscription_phone_numbers_response.py
prelude_python_sdk-0.10.0.dist-info/METADATA
prelude_python_sdk-0.10.0.dist-info/WHEEL
prelude_python_sdk-0.10.0.dist-info/licenses/LICENSE
prelude_python_sdk-0.10.0.dist-info/RECORD
